sunsynkloggerapi/__init__.py
sunsynkloggerapi/const.py
sunsynkloggerapi/sensor.py
sunsynkloggerapi-0.0.22.dist-info/LICENSE
sunsynkloggerapi-0.0.22.dist-info/METADATA
sunsynkloggerapi-0.0.22.dist-info/WHEEL
sunsynkloggerapi-0.0.22.dist-info/top_level.txt
sunsynkloggerapi-0.0.22.dist-info/RECORD
