Metadata-Version: 2.1
Name: sunsynkloggerapi
Version: 0.0.22
Summary: SynSynk Logger API Python Library
Home-page: https://github.com/StickeyTape/sunsynkloggerapi
Author: Jacques Coetzer
Project-URL: Bug Reports, https://github.com/StickeyTape/sunsynkloggerapi/issues
Project-URL: Source, https://github.com/StickeyTape/sunsynkloggerapi/
Keywords: inverter,sunsynk,logger,python,library
Classifier: Development Status :: 3 - Alpha
Classifier: Intended Audience :: Developers
Classifier: Topic :: Home Automation
Classifier: Topic :: Software Development :: Libraries :: Python Modules
Classifier: License :: OSI Approved :: MIT License
Classifier: Programming Language :: Python :: 3.8
Classifier: Programming Language :: Python :: 3.9
Classifier: Programming Language :: Python :: 3.10
Requires-Python: >=3.8, <4
License-File: LICENSE
Requires-Dist: aiohttp
Requires-Dist: asyncio
Requires-Dist: voluptuous
Requires-Dist: python-dateutil
